{
  "project_info": {
    "project_number": "782930863049",
    "firebase_url": "https://tastyclarify-6a322.firebaseio.com",
    "project_id": "tastyclarify-6a322",
    "storage_bucket": "tastyclarify-6a322.appspot.com"
  },
  "client": [
    {
      "client_info": {
        "mobilesdk_app_id": "1:782930863049:android:7b100bd39dfce119",
        "android_client_info": {
          "package_name": "com.vnwarriors.tastyclarify"
        }
      },
      "oauth_client": [
        {
          "client_id": "782930863049-c36g0a9lkdgog1u64m55qpgd5d8uukd2.apps.googleusercontent.com",
          "client_type": 1,
          "android_info": {
            "package_name": "com.vnwarriors.tastyclarify",
            "certificate_hash": "EBA80F57EF8A327B1A7492A423E1A529007113ED"
          }
        },
        {
          "client_id": "782930863049-hfgkbvg0oisjstg1jjhuctob9b3un6c9.apps.googleusercontent.com",
          "client_type": 1,
          "android_info": {
            "package_name": "com.vnwarriors.tastyclarify",
            "certificate_hash": "E48F76181BFC0A4D185BDDC1E576A4D2CBA83D0D"
          }
        },
        {
          "client_id": "782930863049-d9paerkh5eipj8ocpe07jbtkkl1la12i.apps.googleusercontent.com",
          "client_type": 3
        }
      ],
      "api_key": [
        {
          "current_key": "AIzaSyAtgmB5HUBYVEsL3Za8Y0s1zyiIjNlwcXo"
        }
      ],
      "services": {
        "analytics_service": {
          "status": 1
        },
        "appinvite_service": {
          "status": 2,
          "other_platform_oauth_client": [
            {
              "client_id": "782930863049-d9paerkh5eipj8ocpe07jbtkkl1la12i.apps.googleusercontent.com",
              "client_type": 3
            }
          ]
        },
        "ads_service": {
          "status": 2
        }
      }
    }
  ],
  "configuration_version": "1"
}